{
  "Todos": [
    {
      "name": "1",
      "done": false,
      "id": 1
    },
    {
      "name": "2",
      "done": false,
      "id": 2
    },
    {
      "name": "3",
      "done": false,
      "id": 3
    },
    {
      "name": "4",
      "done": false,
      "id": 4
    },
    {
      "name": "5",
      "done": false,
      "id": 5
    },
    {
      "name": "6",
      "done": false,
      "id": 6
    },
    {
      "name": "7",
      "done": false,
      "id": 7
    },
    {
      "name": "8",
      "done": false,
      "id": 8
    },
    {
      "name": "9",
      "done": false,
      "id": 9
    },
    {
      "name": "11",
      "done": false,
      "id": 10
    }
  ]
}